pk2api/__init__.py
pk2api/cli.py
pk2api/comparison.py
pk2api/pk2_file.py
pk2api/pk2_folder.py
pk2api/pk2_stream.py
pk2api/structures.py
pk2api/security/__init__.py
pk2api/security/blowfish.py
pk2api-1.5.0.dist-info/METADATA
pk2api-1.5.0.dist-info/WHEEL
pk2api-1.5.0.dist-info/entry_points.txt
pk2api-1.5.0.dist-info/top_level.txt
pk2api-1.5.0.dist-info/RECORD
