Metadata-Version: 2.4
Name: pk2api
Version: 1.5.0
Summary: Python library to read and write Silkroad Online PK2 files
Author: dadav
License: MIT
Project-URL: Homepage, https://github.com/ddavid/SRO.PK2API
Keywords: silkroad,pk2,mmorpg,game,archive
Classifier: Development Status :: 4 - Beta
Classifier: Intended Audience :: Developers
Classifier: License :: OSI Approved :: MIT License
Classifier: Operating System :: OS Independent
Classifier: Programming Language :: Python :: 3
Classifier: Programming Language :: Python :: 3.10
Classifier: Programming Language :: Python :: 3.11
Classifier: Programming Language :: Python :: 3.12
Classifier: Topic :: Games/Entertainment
Classifier: Topic :: Software Development :: Libraries :: Python Modules
Requires-Python: >=3.10
Requires-Dist: rich>=14.2.0
